LICENCE.txt
MANIFEST.in
README.rst
setup.cfg
setup.py
sample/__init__.py
sample/exceptions.py
sample/hello.py
sample/logger.py
sample/cli/__init__.py
sample/cli/entrypoint.py
sample/cli/greet.py
sample/cli/version.py
sveetch_python_sample.egg-info/PKG-INFO
sveetch_python_sample.egg-info/SOURCES.txt
sveetch_python_sample.egg-info/dependency_links.txt
sveetch_python_sample.egg-info/entry_points.txt
sveetch_python_sample.egg-info/requires.txt
sveetch_python_sample.egg-info/top_level.txt
sveetch_python_sample.egg-info/zip-safe