Metadata-Version: 2.1
Name: sveetch-python-sample
Version: 0.4.0
Summary: A project example created from cookiecutter-sveetch-python.
Home-page: https://github.com/sveetch/sveetch-python-sample
Author: David Thenon
Author-email: sveetch@gmail.com
License: MIT
Project-URL: Source Code, https://github.com/sveetch/sveetch-python-sample
Project-URL: Issue Tracker, https://github.com/sveetch/sveetch-python-sample/issues
Project-URL: Changelog, https://sveetch-python-sample.readthedocs.io/en/latest/history.html
Project-URL: Documentation, https://sveetch-python-sample.readthedocs.io/
Keywords: Python
Classifier: Development Status :: 2 - Pre-Alpha
Classifier: Intended Audience :: Developers
Classifier: License :: OSI Approved :: MIT License
Classifier: Natural Language :: English
Classifier: Programming Language :: Python :: 3
Classifier: Programming Language :: Python :: 3.8
Classifier: Programming Language :: Python :: 3.9
Classifier: Programming Language :: Python :: 3.10
Provides-Extra: dev
Provides-Extra: quality
Provides-Extra: doc
License-File: LICENCE.txt
